pytest_xpara/__init__.py
pytest_xpara/plugin.py
pytest_xpara-0.3.0.dist-info/LICENSE
pytest_xpara-0.3.0.dist-info/METADATA
pytest_xpara-0.3.0.dist-info/WHEEL
pytest_xpara-0.3.0.dist-info/entry_points.txt
pytest_xpara-0.3.0.dist-info/top_level.txt
pytest_xpara-0.3.0.dist-info/RECORD
