Metadata-Version: 2.1
Name: pytest-xpara
Version: 0.3.0
Summary: An extended parametrizing plugin of pytest.
Home-page: https://github.com/tonyseek/pytest-xpara
Author: Jiangge Zhang
Author-email: tonyseek@gmail.com
License: MIT
Keywords: pytest,parametrize,yaml,toml
Platform: any
Classifier: Development Status :: 3 - Alpha
Classifier: Environment :: Plugins
Classifier: Intended Audience :: Developers
Classifier: License :: OSI Approved :: MIT License
Classifier: Operating System :: OS Independent
Classifier: Programming Language :: Python :: 3.5
Classifier: Programming Language :: Python :: 3.6
Classifier: Programming Language :: Python :: 3.7
Classifier: Programming Language :: Python :: 3.8
Classifier: Programming Language :: Python :: 3.9
Classifier: Topic :: Software Development :: Testing
Classifier: Topic :: Software Development :: Libraries :: Python Modules
License-File: LICENSE
Requires-Dist: pytest
Provides-Extra: toml
Requires-Dist: toml ; extra == 'toml'
Provides-Extra: yaml
Requires-Dist: PyYAML ; extra == 'yaml'
